numbers_properties_pkg/__init__.py
numbers_properties_pkg/ankitvp.py
Kicking-2.dist-info/LICENSE
Kicking-2.dist-info/METADATA
Kicking-2.dist-info/WHEEL
Kicking-2.dist-info/top_level.txt
Kicking-2.dist-info/RECORD
