Metadata-Version: 2.1
Name: Kicking
Version: 2
Summary: Ankit's package
Home-page: https://github.com/pypa/sampleproject
Author: Ankit
Author-email: jankit2104@gmail.com
License: UNKNOWN
Platform: UNKNOWN
Classifier: Programming Language :: Python :: 3
Classifier: License :: OSI Approved :: MIT License
Classifier: Operating System :: OS Independent
Requires-Python: >=3.6
License-File: LICENSE
